{
  "title": "Restaurant Search",
  "name": "Restaurant Search",
  "db": "restaurant.json",
  "version": 1,
  "api_names": ["restaurant_search"],
  "schema_urls": { "restaurant_search": "https://i.imgur.com/wnmwuOT.jpg" },
  "instructions": {
    "User": {
      "completion_requirements": ["You have found a restaurant."],
      "completion_questions": [
        "...find you a suitable restaurant?",
        "...stay calm and helpful throughout the dialogue?"
      ],
      "task_description": "Search for The Porch near the Center part of town."
    },
    "Wizard": {
      "task_description": "Help the user find a restaurant.",
      "completion_requirements": [
        "You have found a restaurant that the user likes,",
        "or the user says goodbye."
      ],
      "completion_questions": [
        "...change his/her mind about what he/she wants at any time?",
        "...become aggressive or annoyed during the dialogue?"
      ]
    }
  }
}
